Metadata-Version: 2.1
Name: pybooks
Version: 1.4.3
Summary: Find a book download URL from multiple online book sources
Home-page: https://github.com/AnhVanGiang/pybooks
Author: Anh Van Giang
Author-email: vangianganh@gmail.com
License: MIT
Download-URL: https://github.com/AnhVanGiang/pybooks/archive/v_15.tar.gz
Keywords: scraper,books,python
Platform: UNKNOWN
Classifier: Development Status :: 4 - Beta
Classifier: Intended Audience :: Developers
Classifier: Topic :: Software Development :: Build Tools
Classifier: License :: OSI Approved :: MIT License
Classifier: Programming Language :: Python :: 3.1
Classifier: Programming Language :: Python :: 3.2
Classifier: Programming Language :: Python :: 3.3
Classifier: Programming Language :: Python :: 3.4
Classifier: Programming Language :: Python :: 3.5
